flake8_docstrings.py
flake8_docstrings_catnado-0.0.1.dev1.dist-info/METADATA
flake8_docstrings_catnado-0.0.1.dev1.dist-info/RECORD
flake8_docstrings_catnado-0.0.1.dev1.dist-info/WHEEL
flake8_docstrings_catnado-0.0.1.dev1.dist-info/entry_points.txt
flake8_docstrings_catnado-0.0.1.dev1.dist-info/top_level.txt
