Metadata-Version: 2.1
Name: flake8-docstrings-catnado
Version: 0.0.1.dev1
Summary: a fork of flake8-docstrings-catnado
Home-page: https://github.com/tylertrussell/flake8-docstrings-catnado
Author: Tyler Trussell
Author-email: tigertrussell@gmail.com
License: MIT License
Platform: UNKNOWN
Provides: flake8_docstrings
Requires-Dist: flake8
Requires-Dist: pydocstyle (>=2.1)
Requires-Dist: flake8-polyfill
